CHANGES.rst
MANIFEST.in
README.rst
main.py
setup.cfg
setup.py
pyodcompare/__init__.py
pyodcompare/compare.py
pyodcompare/tests.py
pyodcompare.egg-info/PKG-INFO
pyodcompare.egg-info/SOURCES.txt
pyodcompare.egg-info/dependency_links.txt
pyodcompare.egg-info/entry_points.txt
pyodcompare.egg-info/not-zip-safe
pyodcompare.egg-info/requires.txt
pyodcompare.egg-info/top_level.txt
pyodcompare/test_data/documentv1.doc
pyodcompare/test_data/documentv2.doc