Metadata-Version: 1.1
Name: pyodcompare
Version: 0.2
Summary: Generate a comparaison of two libreoffice documents using uno
Home-page: https://github.com/IMIO/pyodcompare
Author: Thomas Desvenain
Author-email: thomas.desvenain@gmail.com
License: GPL v3
Keywords: libreoffice openoffice
Platform: UNKNOWN
Classifier: Programming Language :: Python
Classifier: Programming Language :: Python :: 2.7
